rayne/__init__.py
rayne/benchmark.py
rayne-0.1.0.dist-info/METADATA
rayne-0.1.0.dist-info/WHEEL
rayne-0.1.0.dist-info/licenses/LICENSE
rayne-0.1.0.dist-info/RECORD
