Metadata-Version: 2.3
Name: Rayne
Version: 0.1.0
Summary: A micro benchmarking utility for Python
Project-URL: Documentation, https://rayne.readthedocs.io
Project-URL: Repository, https://github.com/brobeson/Rayne
Project-URL: Issue Tracker, https://github.com/brobeson/Rayne/issues
Author-email: brobeson <brobeson@users.noreply.github.com>
License: MIT License
Keywords: benchmark,micro-benchmark,microbenchmark,python
Classifier: Development Status :: 1 - Planning
Classifier: Intended Audience :: Developers
Classifier: Operating System :: OS Independent
Classifier: Programming Language :: Python
Classifier: Programming Language :: Python :: 3
Classifier: Programming Language :: Python :: 3.7
Classifier: Programming Language :: Python :: 3.8
Classifier: Programming Language :: Python :: 3.9
Classifier: Programming Language :: Python :: 3.10
Classifier: Programming Language :: Python :: 3.11
Classifier: Programming Language :: Python :: 3.12
Classifier: Topic :: Software Development :: Testing
Requires-Python: >=3.7
